change_extension.py
change_extension-1.1.dist-info/METADATA
change_extension-1.1.dist-info/WHEEL
change_extension-1.1.dist-info/RECORD
