Metadata-Version: 2.1
Name: change_extension
Version: 1.1
Summary: 批量修改文件夹内文件的扩展名
Home-page: https://github.com/myally/change_extension
License: MIT
Author: BlackWhite
Author-email: jierong8215@gmail.com
Requires-Python: >=3.6
Classifier: License :: OSI Approved :: MIT License
Classifier: Programming Language :: Python :: 3
Classifier: Programming Language :: Python :: 3.6
Classifier: Programming Language :: Python :: 3.7
Classifier: Programming Language :: Python :: 3.8
Classifier: Programming Language :: Python :: 3.9
Classifier: Programming Language :: Python :: 3.10
Classifier: Programming Language :: Python :: 3.11
Project-URL: Repository, https://github.com/myally/change_extension
